{
  "version": "7",
  "dialect": "postgresql",
  "entries": [
    {
      "idx": 0,
      "version": "7",
      "when": 1777823967150,
      "tag": "0000_init",
      "breakpoints": true
    },
    {
      "idx": 1,
      "version": "7",
      "when": 1777891523496,
      "tag": "0001_messaging",
      "breakpoints": true
    },
    {
      "idx": 2,
      "version": "7",
      "when": 1777957741685,
      "tag": "0002_billing_entitlements",
      "breakpoints": true
    },
    {
      "idx": 3,
      "version": "7",
      "when": 1777959748037,
      "tag": "0003_agent_actions",
      "breakpoints": true
    }
  ]
}
